napi/__init__.py
napi/api.py
napi/encoding.py
napi/hash.py
napi/main.py
napi/napi.py
napi/read_7z.py
napi/store_subs.py
napi_py-1.2.4.dist-info/LICENSE.md
napi_py-1.2.4.dist-info/METADATA
napi_py-1.2.4.dist-info/WHEEL
napi_py-1.2.4.dist-info/entry_points.txt
napi_py-1.2.4.dist-info/RECORD
