Metadata-Version: 2.1
Name: napi-py
Version: 1.2.4
Summary: CLI tool for downloading subtitles from napiprojekt.pl
Home-page: https://github.com/emkor/napi-py
License: GPL-3.0 License
Keywords: napiprojekt,subs,subtitles,movie,film
Author: emkor93
Author-email: emkor93@gmail.com
Requires-Python: >=3.7,<4.0
Classifier: License :: Other/Proprietary License
Classifier: Programming Language :: Python :: 3
Classifier: Programming Language :: Python :: 3.7
Classifier: Programming Language :: Python :: 3.8
Classifier: Programming Language :: Python :: 3.9
Classifier: Programming Language :: Python :: 3.10
Classifier: Programming Language :: Python :: 3.11
Classifier: Programming Language :: Python :: 3.12
Requires-Dist: chardet (>=5.2.0,<6.0.0)
Requires-Dist: pylzma (>=0.5.0,<0.6.0)
Project-URL: Repository, https://github.com/emkor/napi-py
